Metadata-Version: 2.1
Name: superset-2.0.0-custom-test
Version: 0.0.1
Summary: A modern, enterprise-ready business intelligence web application
Home-page: UNKNOWN
Author: Apache Superset Dev
Author-email: shumeykoa@mail.ru
License: Apache License, Version 2.0
Platform: UNKNOWN
Classifier: Programming Language :: Python :: 3.8
Classifier: Programming Language :: Python :: 3.9
Requires-Python: ~=3.8
Provides-Extra: athena
Provides-Extra: aurora-data-api
Provides-Extra: bigquery
Provides-Extra: clickhouse
Provides-Extra: cockroachdb
Provides-Extra: cors
Provides-Extra: crate
Provides-Extra: databricks
Provides-Extra: db2
Provides-Extra: dremio
Provides-Extra: drill
Provides-Extra: druid
Provides-Extra: elasticsearch
Provides-Extra: exasol
Provides-Extra: excel
Provides-Extra: firebird
Provides-Extra: firebolt
Provides-Extra: gsheets
Provides-Extra: hana
Provides-Extra: hive
Provides-Extra: impala
Provides-Extra: kusto
Provides-Extra: kylin
Provides-Extra: mssql
Provides-Extra: mysql
Provides-Extra: netezza
Provides-Extra: oracle
Provides-Extra: pinot
Provides-Extra: postgres
Provides-Extra: presto
Provides-Extra: prophet
Provides-Extra: redshift
Provides-Extra: rockset
Provides-Extra: shillelagh
Provides-Extra: snowflake
Provides-Extra: solr
Provides-Extra: teradata
Provides-Extra: thumbnails
Provides-Extra: trino
Provides-Extra: vertica
